roll_the_dice/__init__.py
roll_the_dice/cli.py
roll_the_dice/dice.py
roll_the_dice-0.1.0.dist-info/entry_points.txt
roll_the_dice-0.1.0.dist-info/WHEEL
roll_the_dice-0.1.0.dist-info/METADATA
roll_the_dice-0.1.0.dist-info/RECORD
