Metadata-Version: 2.1
Name: roll-the-dice
Version: 0.1.0
Summary: 
Author: Guilherme
Author-email: marquesguilherme3@gmail.com
Requires-Python: >=3.8,<4.0
Classifier: Programming Language :: Python :: 3
Classifier: Programming Language :: Python :: 3.8
Classifier: Programming Language :: Python :: 3.9
Classifier: Programming Language :: Python :: 3.10
Classifier: Programming Language :: Python :: 3.11
Requires-Dist: typer (>=0.7.0,<0.8.0)
